pureaml/__init__.py
pureaml/anchor.py
pureaml/comments.py
pureaml/compat.py
pureaml/composer.py
pureaml/configobjwalker.py
pureaml/constructor.py
pureaml/cyaml.py
pureaml/docinfo.py
pureaml/dumper.py
pureaml/emitter.py
pureaml/error.py
pureaml/events.py
pureaml/loader.py
pureaml/main.py
pureaml/nodes.py
pureaml/parser.py
pureaml/py.typed
pureaml/reader.py
pureaml/representer.py
pureaml/resolver.py
pureaml/scalarbool.py
pureaml/scalarfloat.py
pureaml/scalarint.py
pureaml/scalarstring.py
pureaml/scanner.py
pureaml/serializer.py
pureaml/tag.py
pureaml/timestamp.py
pureaml/tokens.py
pureaml/util.py
pureyaml/LICENSE
pureyaml/__init__.py
pureyaml/anchor.py
pureyaml/comments.py
pureyaml/compat.py
pureyaml/composer.py
pureyaml/configobjwalker.py
pureyaml/constructor.py
pureyaml/cyaml.py
pureyaml/docinfo.py
pureyaml/dumper.py
pureyaml/emitter.py
pureyaml/error.py
pureyaml/events.py
pureyaml/loader.py
pureyaml/main.py
pureyaml/nodes.py
pureyaml/parser.py
pureyaml/py.typed
pureyaml/reader.py
pureyaml/representer.py
pureyaml/resolver.py
pureyaml/scalarbool.py
pureyaml/scalarfloat.py
pureyaml/scalarint.py
pureyaml/scalarstring.py
pureyaml/scanner.py
pureyaml/serializer.py
pureyaml/setup.py
pureyaml/tag.py
pureyaml/timestamp.py
pureyaml/tokens.py
pureyaml/util.py
ruamel/yaml/LICENSE
ruamel/yaml/__init__.py
ruamel/yaml/anchor.py
ruamel/yaml/comments.py
ruamel/yaml/compat.py
ruamel/yaml/composer.py
ruamel/yaml/configobjwalker.py
ruamel/yaml/constructor.py
ruamel/yaml/cyaml.py
ruamel/yaml/docinfo.py
ruamel/yaml/dumper.py
ruamel/yaml/emitter.py
ruamel/yaml/error.py
ruamel/yaml/events.py
ruamel/yaml/loader.py
ruamel/yaml/main.py
ruamel/yaml/nodes.py
ruamel/yaml/parser.py
ruamel/yaml/py.typed
ruamel/yaml/reader.py
ruamel/yaml/representer.py
ruamel/yaml/resolver.py
ruamel/yaml/scalarbool.py
ruamel/yaml/scalarfloat.py
ruamel/yaml/scalarint.py
ruamel/yaml/scalarstring.py
ruamel/yaml/scanner.py
ruamel/yaml/serializer.py
ruamel/yaml/setup.py
ruamel/yaml/tag.py
ruamel/yaml/timestamp.py
pureaml-0.18.6.dist-info/LICENSE
pureaml-0.18.6.dist-info/METADATA
pureaml-0.18.6.dist-info/WHEEL
pureaml-0.18.6.dist-info/top_level.txt
pureaml-0.18.6.dist-info/RECORD
